dbc/__init__.py
dbc/cyprien_code.py
dbc/main.py
dbc/utils.py
dbc/discretizers/__init__.py
dbc/discretizers/base.py
dbc/discretizers/cmeans.py
dbc/discretizers/cmeans_class_wise.py
dbc/discretizers/kmeans.py
dbc/discretizers/kmeans_class_wise.py
dbc_menamot-2.0.1.dist-info/LICENSE
dbc_menamot-2.0.1.dist-info/METADATA
dbc_menamot-2.0.1.dist-info/WHEEL
dbc_menamot-2.0.1.dist-info/top_level.txt
dbc_menamot-2.0.1.dist-info/RECORD
