Metadata-Version: 2.1
Name: dbc-menamot
Version: 2.0.1
Summary: A Python package for Discrete Bayesian and Minmax Classifiers
Home-page: https://github.com/Menamot/dbc
Author: Wenlong
Author-email: menamot.chen@gmail.com
License: MIT
Classifier: Programming Language :: Python :: 3
Classifier: License :: OSI Approved :: MIT License
Classifier: Operating System :: OS Independent
Classifier: Topic :: Scientific/Engineering :: Artificial Intelligence
Requires-Python: >=3.11
License-File: LICENSE
Requires-Dist: numpy ==2.3.4
Requires-Dist: scikit-learn ==1.7.2
Requires-Dist: scikit-fuzzy ==0.5.0
